ros_uncrustify_vendor-3.1.0.data/data/opt/uncrustify_vendor/bin/uncrustify
ros_uncrustify_vendor-3.1.0.data/data/share/ament_index/resource_index/package_run_dependencies/uncrustify_vendor
ros_uncrustify_vendor-3.1.0.data/data/share/ament_index/resource_index/packages/uncrustify_vendor
ros_uncrustify_vendor-3.1.0.data/data/share/ament_index/resource_index/parent_prefix_path/uncrustify_vendor
ros_uncrustify_vendor-3.1.0.data/data/share/ament_index/resource_index/vendor_packages/uncrustify_vendor
ros_uncrustify_vendor-3.1.0.data/data/share/uncrustify_vendor/local_setup.bash
ros_uncrustify_vendor-3.1.0.data/data/share/uncrustify_vendor/local_setup.dsv
ros_uncrustify_vendor-3.1.0.data/data/share/uncrustify_vendor/local_setup.sh
ros_uncrustify_vendor-3.1.0.data/data/share/uncrustify_vendor/local_setup.zsh
ros_uncrustify_vendor-3.1.0.data/data/share/uncrustify_vendor/package.dsv
ros_uncrustify_vendor-3.1.0.data/data/share/uncrustify_vendor/package.xml
ros_uncrustify_vendor-3.1.0.data/data/share/uncrustify_vendor/cmake/uncrustify_vendorConfig-version.cmake
ros_uncrustify_vendor-3.1.0.data/data/share/uncrustify_vendor/cmake/uncrustify_vendorConfig.cmake
ros_uncrustify_vendor-3.1.0.data/data/share/uncrustify_vendor/cmake/vendor_package_cmake_prefix.cmake
ros_uncrustify_vendor-3.1.0.data/data/share/uncrustify_vendor/environment/ament_prefix_path.dsv
ros_uncrustify_vendor-3.1.0.data/data/share/uncrustify_vendor/environment/ament_prefix_path.sh
ros_uncrustify_vendor-3.1.0.data/data/share/uncrustify_vendor/environment/path.dsv
ros_uncrustify_vendor-3.1.0.data/data/share/uncrustify_vendor/environment/path.sh
ros_uncrustify_vendor-3.1.0.data/data/share/uncrustify_vendor/environment/vendor_package.bat
ros_uncrustify_vendor-3.1.0.data/data/share/uncrustify_vendor/environment/vendor_package.dsv
ros_uncrustify_vendor-3.1.0.data/data/share/uncrustify_vendor/environment/vendor_package.sh
uncrustify_vendor/_dummy.cpython-310-x86_64-linux-gnu.so
ros_uncrustify_vendor-3.1.0.dist-info/METADATA
ros_uncrustify_vendor-3.1.0.dist-info/WHEEL
ros_uncrustify_vendor-3.1.0.dist-info/top_level.txt
ros_uncrustify_vendor-3.1.0.dist-info/RECORD
ros_uncrustify_vendor-3.1.0.dist-info/licenses/LICENSE
