Metadata-Version: 2.4
Name: ros-uncrustify-vendor
Version: 3.1.0
Summary: A ROS package providing a CMake shim for the uncrustify code beautifier library.
License-File: LICENSE
Dynamic: description
Dynamic: description-content-type
Dynamic: license-file
Dynamic: summary
